{
    "game_save": {
        "game_stat": {
            "game_mod": "pvp",
            "round": 13,
            "player_turn": "hrac2",
            "last_dice": [
                2,
                1
            ],
            "spikes": [
                [
                    1,
                    "bila",
                    [
                        1
                    ]
                ],
                [
                    1,
                    "bila",
                    [
                        1
                    ]
                ],
                [
                    1,
                    "bila",
                    [
                        1
                    ]
                ],
                [
                    2,
                    "bila",
                    [
                        2
                    ]
                ],
                [
                    5,
                    "bila",
                    []
                ],
                [
                    5,
                    "bila",
                    []
                ],
                [
                    5,
                    "bila",
                    []
                ],
                [
                    5,
                    "bila",
                    []
                ],
                [
                    8,
                    "bila",
                    [
                        3,
                        8
                    ]
                ],
                [
                    10,
                    "bila",
                    [
                        10
                    ]
                ],
                [
                    11,
                    "cerna",
                    []
                ],
                [
                    11,
                    "cerna",
                    []
                ],
                [
                    11,
                    "cerna",
                    []
                ],
                [
                    13,
                    "bila",
                    []
                ],
                [
                    13,
                    "bila",
                    []
                ],
                [
                    13,
                    "bila",
                    []
                ],
                [
                    14,
                    "cerna",
                    [
                        14
                    ]
                ],
                [
                    16,
                    "cerna",
                    []
                ],
                [
                    16,
                    "cerna",
                    []
                ],
                [
                    16,
                    "cerna",
                    []
                ],
                [
                    16,
                    "cerna",
                    [
                        16
                    ]
                ],
                [
                    18,
                    "cerna",
                    [
                        9,
                        18
                    ]
                ],
                [
                    19,
                    "cerna",
                    []
                ],
                [
                    19,
                    "cerna",
                    []
                ],
                [
                    19,
                    "cerna",
                    []
                ],
                [
                    19,
                    "cerna",
                    []
                ],
                [
                    19,
                    "cerna",
                    []
                ],
                [
                    23,
                    "bila",
                    []
                ],
                [
                    23,
                    "bila",
                    []
                ]
            ],
            "bar": [],
            "domecky": []
        },
        "player1": {
            "name": "hrac1"
        },
        "player2": {
            "name": "hrac2"
        }
    }
}